{"cookies": [], "origins": [{"origin": "https://nikita-filonov.github.io", "localStorage": [{"name": "persist:users", "value": "{\"user\":\"{\\\"id\\\":\\\"972146ba-74d9-4809-b131-df0bc0e3fd9a\\\",\\\"email\\\":\\\"user.name@gmail.com\\\",\\\"username\\\":\\\"username\\\",\\\"password\\\":\\\"password\\\"}\",\"users\":\"[{\\\"id\\\":\\\"972146ba-74d9-4809-b131-df0bc0e3fd9a\\\",\\\"email\\\":\\\"user.name@gmail.com\\\",\\\"username\\\":\\\"username\\\",\\\"password\\\":\\\"password\\\"}]\",\"_persist\":\"{\\\"version\\\":-1,\\\"rehydrated\\\":true}\"}"}, {"name": "persist:courses", "value": "{\"course\":\"{\\\"id\\\":\\\"\\\",\\\"title\\\":\\\"\\\",\\\"userId\\\":\\\"\\\",\\\"maxScore\\\":0,\\\"minScore\\\":0,\\\"exercises\\\":[],\\\"description\\\":\\\"\\\",\\\"previewImage\\\":null,\\\"estimatedTime\\\":\\\"\\\"}\",\"courses\":\"[]\",\"_persist\":\"{\\\"version\\\":-1,\\\"rehydrated\\\":true}\"}"}]}]}